LICENSE
MANIFEST.in
coin
setup.py
version
coin.egg-info/PKG-INFO
coin.egg-info/SOURCES.txt
coin.egg-info/dependency_links.txt
coin.egg-info/requires.txt
coin.egg-info/top_level.txt
coinlib/__init__.py
coinlib/debian.py
coinlib/python.py
coinlib/raw.py
coinlib/util.py
test/test_install.py