Metadata-Version: 1.0
Name: coin
Version: 0.20
Summary: Copy Installer
Home-page: https://github.com/syncloud/coin
Author: Syncloud
Author-email: support@syncloud.it
License: GPLv3
Platform: UNKNOWN
